django_admin_reset/__init__.py
django_admin_reset/admin.py
django_admin_reset/locale/hu/LC_MESSAGES/django.mo
django_admin_reset/locale/hu/LC_MESSAGES/django.po
django_admin_reset/templates/admin/add_user_form.html
django_admin_reset/templates/admin/change_user.html
django_admin_reset/templates/admin/password_reset_url.html
django_admin_reset/templates/auth/widgets/read_only_password_hash.html
django_admin_reset-0.7.3.dist-info/licenses/LICENSE
django_admin_reset-0.7.3.dist-info/METADATA
django_admin_reset-0.7.3.dist-info/WHEEL
django_admin_reset-0.7.3.dist-info/top_level.txt
django_admin_reset-0.7.3.dist-info/RECORD
