Metadata-Version: 2.4
Name: django-admin-reset
Version: 0.7.3
Summary: Django admin password reset
Author-email: Tibor Hári <hartib@gmail.com>
License-Expression: BSD-3-Clause
Project-URL: Homepage, https://github.com/tiborhari/django-admin-reset/
Project-URL: Repository, https://github.com/tiborhari/django-admin-reset.git
Project-URL: Bug Tracker, https://github.com/tiborhari/django-admin-reset/issues
Classifier: Development Status :: 4 - Beta
Classifier: Framework :: Django
Classifier: Framework :: Django :: 4.2
Classifier: Framework :: Django :: 5.0
Classifier: Framework :: Django :: 5.1
Classifier: Framework :: Django :: 5.2
Classifier: Programming Language :: Python
Classifier: Programming Language :: Python :: 3
Classifier: Programming Language :: Python :: 3.9
Classifier: Programming Language :: Python :: 3.10
Classifier: Programming Language :: Python :: 3.11
Classifier: Programming Language :: Python :: 3.12
Requires-Python: <4,>=3.9
License-File: LICENSE
Requires-Dist: django<6,>4.2
Provides-Extra: testing
Requires-Dist: flake8~=6.0.0; extra == "testing"
Requires-Dist: pytest~=7.3.1; extra == "testing"
Requires-Dist: pytest-cov~=4.1.0; extra == "testing"
Requires-Dist: pytest-django~=4.5.2; extra == "testing"
Requires-Dist: tox~=4.5.2; extra == "testing"
Provides-Extra: docs
Requires-Dist: sphinx~=7.3.7; extra == "docs"
Requires-Dist: sphinx_rtd_theme~=2.0.0; extra == "docs"
Provides-Extra: babel
Requires-Dist: babel~=2.17.0; extra == "babel"
Dynamic: license-file
